{
	"class" : {
		"allManagers" : "ab 3/31/2003 20:45",
		"classModified:" : "dkh 01/07/2008 14:50",
		"classMoved:" : "dkh 01/07/2008 14:49",
		"classRemoved:" : "dkh 01/07/2008 14:49",
		"forPackage:" : "topa 04/02/2013 05:31",
		"managersForCategory:do:" : "dkh 01/07/2008 14:28",
		"managersForClass:category:do:" : "dkh 01/07/2008 14:32",
		"managersForClass:do:" : "dkh 01/07/2008 14:33",
		"managersForClass:selector:do:" : "dkh 01/07/2008 14:35",
		"methodModified:" : "dkh 01/07/2008 14:49",
		"methodMoved:" : "dkh 01/07/2008 14:52",
		"methodRemoved:" : "dkh 01/07/2008 14:52",
		"registerForNotifications" : "DaleHenrichs 03/11/2011 11:28",
		"registry" : "stephaneducasse 2/4/2006 20:47" },
	"instance" : {
		"initialize" : "topa 04/02/2013 05:29",
		"initializeWithPackage:" : "stephaneducasse 2/4/2006 20:47",
		"modified" : "topa 05/21/2013 08:07",
		"modified:" : "topa 04/02/2013 05:27",
		"package" : "ab 7/7/2003 16:47",
		"packageInfo" : "ab 7/7/2003 13:33",
		"packageName" : "ab 7/7/2003 12:18",
		"packageNameWithStar" : "ab 7/5/2003 23:18",
		"unregister" : "abc 05/21/2013 07:49",
		"unregisterSubpackages" : "dtl 1/11/2011 23:30",
		"update:" : "dkh 08/09/2007 10:57" } }
